browserist/__init__.py
browserist/py.typed
browserist/version.py
browserist/browser/__init__.py
browserist/browser/__main__.py
browserist/browser/check_if/__init__.py
browserist/browser/check_if/__main__.py
browserist/browser/check_if/contains_any_text.py
browserist/browser/check_if/contains_text.py
browserist/browser/check_if/does_exist.py
browserist/browser/check_if/is_clickable.py
browserist/browser/check_if/is_disabled.py
browserist/browser/check_if/is_displayed.py
browserist/browser/check_if/is_enabled.py
browserist/browser/check_if/is_image_loaded.py
browserist/browser/check_if/is_in_viewport.py
browserist/browser/check_if/is_selected.py
browserist/browser/click/__init__.py
browserist/browser/click/__main__.py
browserist/browser/click/button.py
browserist/browser/click/button_if_contains_text.py
browserist/browser/click/download.py
browserist/browser/click/download_and_get_file_path.py
browserist/browser/combo/__init__.py
browserist/browser/combo/__main__.py
browserist/browser/combo/cookie_banner.py
browserist/browser/combo/log_in.py
browserist/browser/combo/search.py
browserist/browser/get/__init__.py
browserist/browser/get/__main__.py
browserist/browser/get/dimensions.py
browserist/browser/get/element.py
browserist/browser/get/elements.py
browserist/browser/get/elements_by_tag.py
browserist/browser/get/meta_description.py
browserist/browser/get/meta_robots.py
browserist/browser/get/page_title.py
browserist/browser/get/text.py
browserist/browser/get/texts.py
browserist/browser/get/attribute/__init__.py
browserist/browser/get/attribute/__main__.py
browserist/browser/get/attribute/value.py
browserist/browser/get/attribute/values.py
browserist/browser/get/html/__init__.py
browserist/browser/get/html/__main__.py
browserist/browser/get/html/element_inner.py
browserist/browser/get/html/element_outer.py
browserist/browser/get/html/page_source.py
browserist/browser/get/url/__init__.py
browserist/browser/get/url/__main__.py
browserist/browser/get/url/canonical.py
browserist-1.7.15.dist-info/licenses/LICENSE.md
browserist-1.7.15.dist-info/METADATA
browserist-1.7.15.dist-info/WHEEL
browserist-1.7.15.dist-info/top_level.txt
browserist-1.7.15.dist-info/RECORD
