Metadata-Version: 2.4
Name: browserist
Version: 1.7.15
Summary: Extension for the Selenium web driver that makes browser automation even easier
Home-page: https://jakob-bagterp.github.io/browserist/
Download-URL: https://pypi.org/project/browserist/
Author: Jakob Bagterp
Author-email: jakob_bagterp@hotmail.com
Maintainer: Jakob Bagterp
Maintainer-email: jakob_bagterp@hotmail.com
License: Apache-2.0
Project-URL: Bug Tracker, https://github.com/jakob-bagterp/browserist/issues
Project-URL: Documentation, https://jakob-bagterp.github.io/browserist/
Project-URL: API Reference, https://jakob-bagterp.github.io/browserist/reference/
Project-URL: Source Code, https://github.com/jakob-bagterp/browserist
Project-URL: Release Notes, https://github.com/jakob-bagterp/browserist/releases
Keywords: python,selenium,browser,automation
Platform: unix
Platform: linux
Platform: osx
Platform: cygwin
Platform: win32
Classifier: Programming Language :: Python :: 3
Classifier: Programming Language :: Python :: 3 :: Only
Classifier: Programming Language :: Python :: 3.11
Classifier: Programming Language :: Python :: 3.12
Classifier: Programming Language :: Python :: 3.13
Classifier: Programming Language :: Python :: 3.14
Classifier: License :: OSI Approved :: Apache Software License
Classifier: Operating System :: OS Independent
Requires-Python: >=3.11
License-File: LICENSE.md
Requires-Dist: lxml==6.0.2
Requires-Dist: pillow==11.3.0
Requires-Dist: requests==2.32.5
Requires-Dist: selenium==4.39.0
Provides-Extra: testing
Requires-Dist: coverage==7.13.1; extra == "testing"
Requires-Dist: flake8==7.3.0; extra == "testing"
Requires-Dist: keyring==25.6.0; extra == "testing"
Requires-Dist: mypy==1.17.1; extra == "testing"
Requires-Dist: pytest==9.0.2; extra == "testing"
Requires-Dist: pytest-cov==7.0.0; extra == "testing"
Requires-Dist: tox==4.32.0; extra == "testing"
Dynamic: download-url
Dynamic: license-file
